<?xml version="1.0" encoding="utf-8" ?>
<c2layout>
    <name>Chapitre3</name>
    <sid>139259355139686</sid>
    <event-sheet>ES_Chapitre3</event-sheet>
    <size>
        <width>1280</width>
        <height>1280</height>
    </size>
    <margins>
        <horizontal>500</horizontal>
        <vertical>500</vertical>
    </margins>
    <unbounded-scrolling>0</unbounded-scrolling>
    <layers>
        <layer name="Background" sid="133663370411091">
            <initially-visible>1</initially-visible>
            <background-color>0,0,0</background-color>
            <transparent>0</transparent>
            <parallax>
                <x>1</x>
                <y>1</y>
            </parallax>
            <zoom-rate>1</zoom-rate>
            <opacity>1</opacity>
            <force-own-texture>0</force-own-texture>
            <global>0</global>
            <use-render-cells>0</use-render-cells>
            <blend-mode>0</blend-mode>
            <effect-fallback>0</effect-fallback>
            <instances />
            <effects />
        </layer>
        <layer name="Ground" sid="533958811980202">
            <initially-visible>1</initially-visible>
            <background-color>255,255,255</background-color>
            <transparent>1</transparent>
            <parallax>
                <x>1</x>
                <y>1</y>
            </parallax>
            <zoom-rate>1</zoom-rate>
            <opacity>1</opacity>
            <force-own-texture>0</force-own-texture>
            <global>0</global>
            <use-render-cells>0</use-render-cells>
            <blend-mode>0</blend-mode>
            <effect-fallback>0</effect-fallback>
            <instances>
                <instance type="Tower_ground" uid="289">
                    <properties>
                        <initial-visibility>Visible</initial-visibility>
                        <tile-width>32</tile-width>
                        <tile-height>32</tile-height>
                        <tile-x-offset>0</tile-x-offset>
                        <tile-y-offset>0</tile-y-offset>
                        <tile-x-spacing>0</tile-x-spacing>
                        <tile-y-spacing>0</tile-y-spacing>
                        <seamless-mode>On</seamless-mode>
                    </properties>
                    <blend-mode>0</blend-mode>
                    <effect-fallback>0</effect-fallback>
                    <world>
                        <x>0</x>
                        <y>0</y>
                        <z>0</z>
                        <width>1280</width>
                        <height>1280</height>
                        <depth>0</depth>
                        <hotspotX>0</hotspotX>
                        <hotspotY>0</hotspotY>
                        <opacity>1</opacity>
                    </world>
                    <tilemap-data>
                        <width>40</width>
                        <height>40</height>
                        <max-width>40</max-width>
                        <max-height>40</max-height>
                        <data>4,0,0,0,0,0,0,0,0,0,0,0,0,0,0,0,0,0,0,0,0,0,0,0,0,0,0,0,0,0,0,0,0,0,0,0,0,0,0,4,0,6,6,6,6,6,6,6,6,6,6,6,6,6,6,6,6,6,6,6,6,6,6,6,6,6,6,6,6,6,4,6,6,6,6,6,6,6,6,0,0,6,6,6,14,6,6,6,6,6,6,6,6,6,6,6,6,14,6,6,6,6,6,6,6,6,6,6,6,6,6,6,6,6,6,6,6,6,6,0,4,6,6,6,6,6,6,6,6,6,6,6,6,6,6,6,6,6,6,6,6,6,6,6,6,6,6,6,6,14,6,6,6,6,6,6,6,6,6,0,6,6,6,6,6,6,6,6,6,14,6,6,6,6,6,6,6,6,6,6,6,6,6,6,6,6,6,6,6,6,6,6,6,6,6,6,6,6,6,0,6,6,6,6,6,6,6,6,6,6,6,6,6,6,6,6,6,6,6,6,6,6,6,6,6,6,6,6,6,6,6,6,6,6,6,6,6,6,14,0,4,6,6,6,6,6,6,6,6,6,6,6,6,6,6,6,6,6,6,6,6,6,6,6,6,6,6,6,6,6,6,6,6,6,6,6,6,6,6,0,0,6,6,6,6,14,6,6,6,6,6,6,6,6,6,6,6,6,6,6,6,6,6,6,6,6,6,6,6,6,6,6,6,6,6,6,6,6,6,0,0,6,6,6,6,6,6,6,6,6,6,6,6,14,6,6,6,6,6,6,6,6,6,6,6,6,6,6,14,6,6,6,6,6,14,6,6,6,6,0,0,6,6,6,6,6,6,6,6,6,6,6,6,6,6,6,6,6,6,6,6,6,6,14,6,6,6,6,14,6,6,6,6,6,6,6,6,6,6,0,0,6,6,6,6,6,6,6,6,6,6,6,6,6,6,14,6,6,6,6,6,6,6,6,6,6,6,6,6,6,6,6,6,14,6,6,6,6,6,0,0,6,6,6,6,6,6,6,6,6,6,6,6,6,6,6,6,6,6,6,6,6,6,6,6,14,6,6,6,6,6,6,6,6,6,6,6,6,6,0,0,14,6,14,6,6,6,6,6,6,6,6,6,6,6,6,6,6,6,6,6,6,6,6,6,6,6,6,6,6,6,6,6,6,6,6,6,6,6,0,0,6,6,6,6,6,6,6,6,6,6,6,6,6,6,6,6,6,6,6,6,6,6,6,6,6,6,6,6,6,6,6,6,6,6,6,6,6,6,0,0,6,6,6,6,6,6,6,6,6,6,6,6,6,6,6,6,6,6,6,6,6,6,6,6,6,6,6,6,6,6,6,6,6,6,6,6,6,14,0,0,6,6,6,6,6,6,6,6,14,6,6,6,6,6,6,6,6,6,14,6,6,6,6,6,6,6,6,6,6,6,6,6,6,6,6,6,6,6,0,0,6,6,6,6,6,6,6,6,6,6,6,6,6,6,6,6,6,6,6,6,6,6,6,6,6,6,6,6,6,6,6,6,6,6,6,6,6,6,0,0,6,6,6,6,6,6,6,6,6,6,6,6,6,6,6,6,6,6,6,6,6,6,14,6,6,6,6,6,14,6,6,6,6,6,6,6,6,6,0,0,6,6,6,6,6,6,6,6,6,6,6,6,6,6,6,6,6,6,6,6,6,6,6,6,6,6,6,6,6,6,6,6,6,6,6,6,6,6,0,0,6,14,6,6,6,6,6,6,6,6,6,14,6,6,6,6,6,6,6,6,6,6,6,6,6,6,6,6,6,6,6,6,6,6,6,6,6,6,0,0,6,6,6,6,6,6,6,14,6,6,6,6,6,6,6,6,6,6,6,6,6,6,6,6,6,6,6,6,6,6,6,6,6,6,6,6,4,4,0,0,6,6,6,6,6,6,6,6,6,6,6,6,6,6,6,6,6,6,6,6,6,6,6,6,6,6,6,6,14,6,6,6,6,6,6,6,6,6,0,0,6,6,6,6,6,6,6,6,6,6,6,6,6,6,6,6,6,6,6,6,6,6,6,6,6,6,6,6,6,6,6,6,6,6,6,6,6,6,4,0,6,6,6,6,6,6,6,6,6,6,6,6,6,6,6,6,6,6,6,6,6,6,6,6,6,6,6,6,6,6,6,6,6,6,6,6,6,6,6,0,6,6,6,6,6,6,6,6,6,6,6,6,6,6,6,6,6,6,6,6,6,6,6,6,6,6,6,6,6,6,6,6,6,6,6,6,6,6,6,0,6,6,6,6,6,6,6,6,6,6,6,6,6,6,6,6,6,6,6,6,6,6,14,6,6,6,6,6,6,6,6,6,6,6,6,6,6,14,4,0,6,6,6,6,6,6,6,6,6,6,6,6,6,6,6,6,6,6,6,6,6,6,6,6,6,6,6,6,6,6,6,6,6,6,6,6,6,6,0,0,6,14,6,6,6,6,6,6,6,6,6,6,6,6,6,6,6,6,6,6,14,6,6,6,6,6,6,6,6,6,6,14,6,6,6,6,6,6,0,0,6,6,6,6,6,6,6,6,6,6,6,6,6,6,6,6,6,6,6,6,6,6,6,6,6,6,6,6,14,6,6,6,6,6,6,6,6,6,0,0,6,6,6,6,6,6,6,6,6,6,6,6,6,6,6,6,6,6,6,6,6,6,6,6,6,14,6,6,6,6,6,6,6,6,6,6,14,6,0,0,6,6,6,6,6,6,6,6,6,6,6,6,6,6,6,6,6,6,6,6,6,6,6,6,6,6,6,6,6,6,6,6,6,6,6,6,6,6,0,0,6,6,6,6,6,6,6,6,6,6,6,6,14,6,6,6,6,6,6,6,6,6,6,6,6,6,6,6,6,6,6,6,6,6,6,6,6,6,0,0,6,6,6,6,6,6,6,6,6,6,6,6,6,6,6,6,6,6,14,6,6,6,6,6,6,14,6,6,6,6,6,6,6,6,6,6,6,6,0,0,6,6,6,6,6,6,6,6,6,6,6,6,6,6,6,6,6,6,6,6,6,6,6,6,6,6,6,6,6,6,6,6,6,6,6,6,6,6,0,0,6,6,6,6,6,6,6,6,6,6,6,6,6,6,6,6,6,6,6,6,6,6,6,6,6,6,6,6,6,4,6,6,6,6,6,6,6,6,0,0,6,6,6,6,6,6,6,6,6,6,6,6,6,6,6,6,6,6,6,6,6,6,6,6,6,6,6,6,6,4,6,6,6,6,6,6,6,6,0,0,6,6,6,6,6,6,6,6,6,6,6,6,6,6,6,6,6,6,6,6,6,6,14,6,6,6,6,6,6,6,6,6,6,6,6,6,6,6,0,0,6,14,6,6,6,6,6,6,6,6,6,6,14,6,6,6,6,14,6,6,6,6,6,6,6,6,6,6,6,6,14,6,6,6,6,6,6,14,0,0,6,6,6,6,6,6,6,6,6,6,6,6,6,6,6,6,6,6,6,6,6,6,6,6,6,6,6,6,6,6,6,6,6,6,6,6,6,6,0,4,0,0,0,0,0,0,0,0,0,0,0,0,0,0,0,0,0,0,0,0,0,0,0,0,0,0,0,0,0,0,0,0,0,0,0,0,0,0,4</data>
                    </tilemap-data>
                </instance>
            </instances>
            <effects />
        </layer>
        <layer name="Walls" sid="312952628440360">
            <initially-visible>1</initially-visible>
            <background-color>255,255,255</background-color>
            <transparent>1</transparent>
            <parallax>
                <x>1</x>
                <y>1</y>
            </parallax>
            <zoom-rate>1</zoom-rate>
            <opacity>1</opacity>
            <force-own-texture>0</force-own-texture>
            <global>0</global>
            <use-render-cells>0</use-render-cells>
            <blend-mode>0</blend-mode>
            <effect-fallback>0</effect-fallback>
            <instances>
                <instance type="Tower_walls_decoration" uid="291">
                    <properties>
                        <initial-visibility>Visible</initial-visibility>
                        <tile-width>32</tile-width>
                        <tile-height>32</tile-height>
                        <tile-x-offset>0</tile-x-offset>
                        <tile-y-offset>0</tile-y-offset>
                        <tile-x-spacing>0</tile-x-spacing>
                        <tile-y-spacing>0</tile-y-spacing>
                        <seamless-mode>On</seamless-mode>
                    </properties>
                    <behavior-instances>
                        <behavior-instance type="Solid">
                            <properties>
                                <initial-state>Enabled</initial-state>
                            </properties>
                        </behavior-instance>
                    </behavior-instances>
                    <blend-mode>0</blend-mode>
                    <effect-fallback>0</effect-fallback>
                    <world>
                        <x>0</x>
                        <y>0</y>
                        <z>0</z>
                        <width>1280</width>
                        <height>1280</height>
                        <depth>0</depth>
                        <hotspotX>0</hotspotX>
                        <hotspotY>0</hotspotY>
                        <opacity>1</opacity>
                    </world>
                    <tilemap-data>
                        <width>40</width>
                        <height>40</height>
                        <max-width>40</max-width>
                        <max-height>40</max-height>
                        <data>50,61,61,61,61,61,61,61,61,61,61,61,61,61,61,61,61,61,61,61,61,61,61,61,61,61,61,61,61,61,61,61,61,61,61,61,61,61,61,70,60,15,-1,-1,-1,-1,40,-1,-1,-1,-1,40,-1,-1,-1,40,-1,-1,-1,-1,40,-1,-1,-1,-1,-1,-1,-1,-1,-1,40,-1,-1,-1,-1,-1,40,-1,-1,60,60,16,-1,-1,-1,-1,60,-1,-1,-1,-1,60,-1,-1,-1,60,-1,-1,-1,-1,60,-1,-1,-1,-1,-1,-1,-1,-1,-1,60,-1,-1,-1,-1,-1,60,-1,-1,60,51,61,61,41,-1,-1,60,-1,-1,-1,-1,60,-1,-1,31,60,-1,-1,31,61,60,-1,-1,31,61,61,61,70,-1,-1,60,-1,15,40,-1,-1,60,-1,-1,60,-1,-1,-1,-1,-1,-1,60,-1,-1,-1,-1,60,-1,-1,-1,60,-1,-1,-1,-1,60,-1,-1,-1,-1,-1,-1,60,-1,-1,60,-1,16,60,-1,-1,30,-1,-1,60,-1,-1,-1,-1,-1,-1,51,61,41,-1,-1,60,-1,-1,-1,60,-1,-1,-1,-1,60,-1,-1,-1,-1,-1,-1,60,-1,-1,60,61,61,60,-1,-1,-1,-1,-1,60,50,61,61,70,-1,-1,-1,-1,-1,-1,-1,60,-1,-1,-1,51,61,70,-1,-1,51,61,41,-1,-1,50,61,71,-1,-1,60,-1,-1,30,-1,-1,-1,-1,-1,60,60,-1,-1,60,-1,-1,-1,-1,-1,-1,-1,60,-1,-1,-1,-1,-1,60,-1,-1,-1,-1,-1,-1,-1,60,-1,-1,-1,-1,60,-1,-1,-1,-1,-1,40,-1,-1,60,60,-1,-1,51,61,61,61,61,41,-1,-1,60,-1,-1,-1,-1,-1,60,-1,-1,-1,-1,-1,-1,-1,60,-1,-1,-1,-1,60,-1,-1,-1,-1,-1,60,-1,-1,60,60,-1,-1,-1,-1,40,-1,-1,-1,-1,-1,60,-1,-1,31,61,61,61,61,61,61,61,41,-1,-1,51,61,70,-1,-1,60,61,41,-1,-1,-1,51,61,61,60,60,-1,-1,-1,-1,30,-1,-1,-1,-1,-1,60,-1,-1,-1,-1,-1,15,40,-1,-1,-1,-1,-1,-1,-1,-1,60,-1,-1,60,-1,-1,-1,-1,-1,-1,-1,-1,60,60,-1,-1,31,61,61,61,61,41,-1,-1,60,-1,-1,-1,-1,-1,16,60,-1,-1,-1,-1,-1,-1,-1,-1,60,-1,-1,60,-1,-1,-1,-1,-1,-1,-1,-1,60,60,-1,-1,-1,-1,-1,-1,-1,-1,-1,-1,60,61,41,-1,-1,-1,-1,60,-1,-1,50,61,61,70,-1,-1,60,-1,-1,60,-1,-1,40,-1,-1,40,-1,-1,60,60,-1,-1,-1,-1,-1,-1,-1,-1,-1,-1,60,-1,-1,-1,-1,31,61,60,-1,-1,60,-1,-1,60,-1,-1,60,-1,-1,60,-1,-1,60,-1,-1,60,-1,-1,60,60,-1,-1,50,61,61,61,61,41,-1,-1,60,-1,-1,-1,-1,-1,-1,60,-1,-1,60,-1,-1,60,61,61,60,-1,-1,60,-1,-1,51,61,61,71,-1,-1,60,60,-1,-1,60,15,-1,-1,-1,-1,-1,-1,60,-1,-1,-1,-1,-1,-1,60,-1,-1,60,-1,-1,60,-1,-1,60,-1,-1,60,-1,-1,-1,-1,-1,-1,-1,-1,60,60,-1,-1,60,16,-1,-1,-1,-1,-1,-1,30,-1,-1,31,61,61,61,60,-1,-1,30,-1,-1,30,-1,-1,60,-1,-1,60,-1,-1,-1,-1,-1,-1,-1,-1,60,60,-1,-1,51,61,61,61,61,41,-1,-1,-1,-1,-1,-1,-1,-1,-1,60,-1,-1,-1,-1,-1,-1,-1,-1,60,-1,-1,60,61,61,70,-1,-1,40,-1,-1,60,60,-1,-1,-1,-1,-1,40,-1,-1,-1,-1,-1,-1,-1,-1,-1,-1,-1,60,-1,-1,-1,-1,-1,-1,-1,-1,60,-1,-1,60,-1,-1,60,-1,-1,60,-1,-1,60,60,-1,-1,-1,-1,-1,60,-1,-1,-1,40,-1,-1,-1,-1,50,61,61,61,61,70,-1,-1,-1,40,-1,-1,60,-1,-1,60,-1,-1,30,-1,-1,60,-1,20,60,60,-1,-1,-1,31,61,60,-1,-1,-1,60,-1,-1,-1,-1,60,90,100,-1,-1,60,-1,-1,-1,60,-1,-1,60,-1,-1,60,-1,-1,-1,-1,-1,60,61,61,60,60,-1,-1,-1,-1,-1,60,-1,-1,-1,30,-1,-1,-1,-1,60,91,101,-1,-1,60,41,-1,-1,60,-1,-1,60,-1,-1,60,-1,-1,-1,-1,-1,60,-1,-1,60,60,-1,-1,-1,-1,-1,60,61,61,61,61,61,61,61,61,60,-1,-1,-1,-1,60,-1,-1,-1,60,-1,-1,60,-1,-1,60,61,61,41,-1,-1,30,-1,-1,30,60,61,61,41,-1,-1,60,-1,-1,-1,-1,-1,-1,-1,-1,60,-1,-1,-1,-1,60,-1,-1,-1,60,-1,-1,60,-1,-1,60,-1,-1,-1,-1,-1,-1,-1,-1,-1,60,-1,-1,-1,-1,-1,60,-1,-1,-1,-1,-1,-1,-1,-1,60,-1,-1,50,61,71,-1,-1,-1,60,-1,-1,60,-1,-1,60,-1,-1,-1,-1,-1,-1,-1,-1,-1,60,-1,-1,-1,-1,-1,60,-1,-1,50,61,61,41,-1,-1,60,-1,-1,60,-1,-1,-1,-1,-1,60,-1,-1,60,-1,-1,51,61,61,70,-1,-1,40,-1,-1,40,60,-1,-1,31,61,61,60,-1,-1,60,-1,-1,-1,-1,-1,60,-1,-1,60,-1,-1,-1,-1,-1,60,-1,-1,60,-1,-1,-1,-1,15,60,-1,-1,60,-1,-1,60,60,-1,-1,-1,-1,-1,60,-1,-1,60,-1,-1,-1,-1,-1,60,-1,-1,51,61,70,-1,-1,-1,60,61,61,71,-1,-1,-1,-1,16,51,61,61,71,-1,-1,60,60,-1,-1,-1,-1,-1,60,-1,-1,60,-1,-1,50,61,61,71,-1,-1,-1,-1,60,-1,-1,-1,60,-1,-1,-1,-1,-1,-1,-1,-1,-1,-1,-1,-1,-1,-1,60,60,-1,-1,40,-1,-1,60,-1,-1,60,-1,-1,60,-1,-1,-1,-1,-1,-1,-1,60,-1,-1,-1,60,-1,-1,-1,-1,-1,-1,-1,-1,-1,-1,-1,-1,-1,-1,60,60,-1,-1,60,-1,-1,60,-1,-1,60,-1,-1,60,-1,-1,-1,-1,-1,31,61,60,41,-1,-1,51,61,61,61,61,61,61,61,61,70,-1,-1,40,-1,-1,60,60,-1,-1,60,-1,-1,60,-1,-1,60,-1,-1,60,-1,-1,40,-1,-1,-1,-1,60,-1,-1,-1,-1,-1,-1,-1,-1,-1,-1,-1,-1,60,-1,-1,60,-1,-1,60,60,-1,-1,60,-1,-1,60,-1,-1,60,-1,-1,60,-1,-1,60,-1,-1,-1,-1,60,-1,-1,-1,-1,-1,-1,-1,-1,-1,-1,-1,-1,60,-1,-1,60,-1,-1,60,60,61,61,71,-1,-1,30,-1,-1,60,-1,-1,30,-1,-1,51,61,70,-1,-1,51,61,61,61,61,61,61,61,61,61,41,-1,-1,60,61,61,61,61,61,60,60,-1,-1,-1,-1,-1,-1,-1,-1,60,-1,-1,-1,-1,-1,-1,-1,60,-1,-1,-1,-1,-1,-1,20,60,-1,-1,-1,-1,-1,-1,-1,60,-1,-1,-1,-1,-1,60,60,-1,-1,-1,-1,-1,-1,-1,-1,60,-1,-1,-1,-1,-1,-1,20,60,-1,-1,-1,-1,-1,-1,-1,60,-1,-1,-1,-1,-1,-1,-1,60,-1,-1,-1,-1,-1,60,60,-1,-1,40,-1,-1,40,-1,-1,51,61,61,70,-1,-1,50,61,71,-1,-1,31,61,70,-1,-1,30,-1,-1,50,61,41,-1,-1,30,-1,-1,40,-1,-1,60,60,-1,-1,60,-1,-1,60,-1,-1,-1,-1,-1,60,-1,-1,60,-1,-1,-1,-1,-1,-1,60,-1,-1,-1,-1,-1,60,-1,-1,-1,-1,-1,-1,-1,60,-1,-1,60,60,-1,-1,60,-1,-1,60,-1,-1,-1,-1,-1,60,-1,-1,30,-1,-1,-1,-1,-1,-1,60,-1,-1,-1,-1,-1,60,-1,-1,-1,-1,-1,-1,-1,30,-1,20,60,51,61,61,61,61,61,61,61,61,61,61,61,61,61,61,61,61,61,61,61,61,61,61,61,61,61,61,61,61,61,61,61,61,61,61,61,61,61,61,71</data>
                    </tilemap-data>
                </instance>
                <instance type="MoveToLayout" uid="332">
                    <properties>
                        <initial-visibility>Invisible</initial-visibility>
                        <initial-animation>Default</initial-animation>
                        <initial-frame>0</initial-frame>
                        <collisions>Enabled</collisions>
                    </properties>
                    <instance-variables>
                        <LayoutName>Sequence_finale</LayoutName>
                    </instance-variables>
                    <blend-mode>0</blend-mode>
                    <effect-fallback>0</effect-fallback>
                    <world>
                        <x>162.4375</x>
                        <y>-5.000003815</y>
                        <z>0</z>
                        <width>82</width>
                        <height>86</height>
                        <depth>0</depth>
                        <hotspotX>0.5</hotspotX>
                        <hotspotY>0.5</hotspotY>
                        <angle>-1.57079649</angle>
                        <opacity>1</opacity>
                    </world>
                </instance>
            </instances>
            <effects />
        </layer>
        <layer name="Decoration" sid="640629057193121">
            <initially-visible>1</initially-visible>
            <background-color>255,255,255</background-color>
            <transparent>1</transparent>
            <parallax>
                <x>1</x>
                <y>1</y>
            </parallax>
            <zoom-rate>1</zoom-rate>
            <opacity>1</opacity>
            <force-own-texture>0</force-own-texture>
            <global>0</global>
            <use-render-cells>0</use-render-cells>
            <blend-mode>0</blend-mode>
            <effect-fallback>0</effect-fallback>
            <instances>
                <instance type="Tower_walls_decoration" uid="313">
                    <properties>
                        <initial-visibility>Visible</initial-visibility>
                        <tile-width>32</tile-width>
                        <tile-height>32</tile-height>
                        <tile-x-offset>0</tile-x-offset>
                        <tile-y-offset>0</tile-y-offset>
                        <tile-x-spacing>0</tile-x-spacing>
                        <tile-y-spacing>0</tile-y-spacing>
                        <seamless-mode>On</seamless-mode>
                    </properties>
                    <behavior-instances>
                        <behavior-instance type="Solid">
                            <properties>
                                <initial-state>Disabled</initial-state>
                            </properties>
                        </behavior-instance>
                    </behavior-instances>
                    <blend-mode>0</blend-mode>
                    <effect-fallback>0</effect-fallback>
                    <world>
                        <x>0</x>
                        <y>0</y>
                        <z>0</z>
                        <width>1280</width>
                        <height>1280</height>
                        <depth>0</depth>
                        <hotspotX>0</hotspotX>
                        <hotspotY>0</hotspotY>
                        <opacity>1</opacity>
                    </world>
                    <tilemap-data>
                        <width>40</width>
                        <height>40</height>
                        <max-width>40</max-width>
                        <max-height>40</max-height>
                        <data>-1,-1,-1,-1,-1,-1,-1,-1,-1,-1,-1,-1,-1,-1,-1,-1,-1,-1,-1,-1,-1,-1,-1,-1,-1,-1,-1,-1,-1,-1,-1,-1,-1,-1,-1,-1,-1,-1,-1,-1,5,15,-1,-1,-1,-1,-1,-1,-1,-1,-1,-1,-1,34,-1,-1,-1,-1,-1,-1,-1,-1,-1,-1,-1,-1,-1,62,-1,-1,-1,-1,-1,-1,-1,-1,-1,34,-1,-1,6,16,-1,-1,-1,-1,-1,34,-1,-1,-1,-1,-1,-1,-1,-1,-1,-1,-1,-1,-1,34,-1,-1,-1,-1,-1,62,-1,-1,-1,-1,-1,-1,-1,-1,-1,-1,-1,-1,-1,-1,-1,-1,-1,-1,-1,-1,-1,36,-1,-1,-1,-1,-1,-1,-1,-1,-1,-1,-1,-1,-1,-1,-1,-1,-1,-1,-1,-1,-1,5,15,-1,-1,36,-1,-1,-1,-1,-1,-1,-1,-1,-1,-1,-1,-1,-1,-1,-1,-1,-1,-1,-1,-1,-1,-1,-1,-1,-1,-1,-1,-1,-1,-1,32,-1,-1,-1,-1,6,16,-1,-1,-1,-1,-1,-1,-1,0,-1,-1,-1,-1,-1,-1,-1,-1,-1,-1,-1,-1,-1,-1,-1,-1,-1,-1,-1,-1,-1,-1,-1,-1,-1,-1,-1,-1,-1,-1,-1,-1,-1,-1,-1,-1,-1,-1,-1,-1,-1,-1,-1,-1,-1,-1,-1,-1,-1,-1,-1,-1,-1,-1,-1,-1,-1,-1,-1,-1,-1,-1,-1,-1,-1,-1,-1,-1,-1,-1,-1,-1,-1,-1,-1,-1,-1,-1,-1,-1,-1,-1,-1,-1,-1,-1,-1,-1,-1,-1,-1,-1,-1,-1,-1,-1,-1,-1,-1,-1,-1,-1,-1,-1,-1,-1,-1,-1,-1,-1,-1,-1,-1,-1,-1,-1,-1,-1,-1,-1,-1,34,-1,-1,-1,-1,-1,-1,-1,-1,-1,-1,-1,-1,-1,-1,-1,-1,-1,-1,-1,-1,-1,-1,-1,-1,-1,-1,-1,-1,-1,-1,-1,-1,-1,-1,-1,-1,-1,-1,-1,-1,-1,-1,-1,13,-1,-1,-1,-1,-1,-1,-1,-1,-1,-1,-1,-1,-1,-1,-1,-1,-1,-1,-1,-1,-1,-1,-1,-1,-1,-1,-1,-1,-1,-1,-1,-1,-1,-1,32,-1,-1,-1,-1,14,-1,-1,-1,-1,-1,-1,-1,-1,-1,5,15,-1,34,-1,-1,-1,-1,-1,-1,-1,-1,-1,-1,-1,-1,-1,-1,-1,-1,-1,32,-1,-1,-1,-1,-1,-1,-1,-1,-1,-1,-1,-1,-1,-1,-1,-1,-1,-1,6,16,-1,-1,-1,-1,-1,-1,-1,-1,-1,-1,-1,-1,-1,-1,-1,-1,-1,-1,-1,-1,34,-1,-1,-1,-1,-1,-1,-1,-1,-1,-1,-1,34,-1,-1,-1,-1,36,-1,-1,-1,-1,-1,-1,-1,-1,-1,-1,-1,-1,-1,-1,-1,-1,-1,-1,-1,-1,-1,-1,-1,-1,-1,-1,-1,-1,-1,-1,-1,-1,-1,-1,-1,-1,32,-1,-1,-1,-1,-1,-1,-1,-1,-1,36,-1,-1,-1,-1,-1,-1,-1,-1,-1,-1,-1,-1,-1,-1,-1,-1,-1,-1,-1,-1,-1,-1,-1,-1,-1,-1,-1,-1,-1,-1,-1,-1,-1,-1,-1,-1,-1,-1,-1,-1,-1,-1,-1,-1,-1,-1,36,-1,-1,-1,-1,-1,-1,-1,-1,-1,-1,-1,-1,-1,5,15,-1,-1,-1,-1,-1,-1,-1,-1,-1,-1,-1,-1,-1,-1,-1,-1,-1,-1,-1,-1,-1,-1,-1,-1,-1,-1,-1,-1,-1,-1,-1,-1,-1,-1,-1,-1,-1,-1,6,16,-1,-1,-1,-1,-1,-1,-1,-1,-1,-1,-1,-1,-1,-1,-1,-1,-1,-1,-1,-1,-1,-1,-1,-1,-1,-1,-1,-1,-1,-1,-1,-1,-1,-1,-1,-1,-1,-1,-1,-1,-1,-1,-1,-1,-1,-1,-1,-1,-1,-1,-1,-1,-1,-1,-1,-1,-1,-1,-1,-1,-1,-1,-1,-1,-1,-1,-1,-1,-1,-1,-1,-1,-1,-1,-1,-1,36,-1,-1,-1,-1,-1,-1,34,-1,-1,-1,-1,-1,-1,-1,-1,-1,-1,-1,-1,34,-1,-1,-1,-1,-1,-1,-1,-1,-1,-1,-1,-1,-1,-1,-1,-1,-1,-1,-1,-1,-1,-1,-1,-1,-1,-1,-1,-1,-1,-1,-1,-1,-1,-1,-1,-1,-1,-1,-1,-1,-1,-1,-1,-1,-1,-1,-1,-1,-1,-1,34,-1,-1,-1,-1,10,-1,-1,-1,-1,-1,-1,-1,-1,-1,-1,-1,-1,-1,-1,-1,-1,-1,80,90,100,-1,-1,-1,-1,-1,-1,-1,-1,-1,-1,-1,-1,-1,-1,-1,-1,-1,-1,-1,-1,-1,-1,-1,-1,-1,-1,-1,-1,-1,-1,-1,-1,-1,-1,-1,-1,-1,81,91,101,-1,-1,-1,-1,-1,-1,-1,-1,-1,-1,-1,-1,-1,-1,-1,-1,-1,-1,-1,-1,-1,-1,-1,-1,-1,-1,-1,-1,-1,-1,-1,-1,-1,-1,-1,-1,-1,12,22,-1,-1,-1,-1,-1,-1,-1,-1,-1,-1,-1,-1,-1,-1,-1,-1,-1,-1,-1,-1,-1,-1,-1,-1,-1,-1,-1,-1,32,-1,-1,-1,-1,-1,-1,-1,-1,-1,-1,-1,-1,-1,-1,-1,-1,-1,-1,-1,32,-1,-1,-1,-1,-1,-1,-1,-1,-1,-1,-1,-1,-1,-1,-1,-1,-1,-1,-1,-1,-1,-1,-1,-1,-1,-1,-1,-1,-1,-1,34,-1,-1,-1,-1,-1,-1,-1,-1,-1,-1,-1,-1,-1,-1,-1,-1,-1,-1,-1,-1,-1,-1,-1,-1,-1,34,-1,-1,-1,-1,-1,-1,-1,-1,-1,-1,-1,-1,-1,-1,-1,-1,13,-1,-1,-1,-1,-1,-1,-1,-1,-1,-1,-1,-1,-1,-1,-1,-1,-1,-1,-1,-1,-1,-1,-1,-1,-1,-1,-1,-1,-1,-1,-1,-1,-1,-1,-1,-1,-1,-1,-1,14,-1,-1,-1,-1,-1,-1,-1,-1,-1,-1,36,5,15,-1,-1,-1,-1,34,-1,-1,-1,-1,-1,-1,-1,-1,-1,-1,-1,-1,-1,-1,-1,-1,-1,-1,-1,-1,-1,-1,-1,-1,-1,-1,-1,-1,-1,-1,-1,-1,-1,6,16,-1,-1,-1,-1,-1,-1,-1,-1,-1,32,-1,-1,-1,-1,-1,-1,-1,-1,-1,-1,-1,-1,-1,-1,-1,-1,-1,-1,-1,-1,-1,-1,-1,-1,-1,-1,-1,-1,-1,-1,-1,-1,-1,-1,-1,-1,-1,-1,-1,-1,-1,-1,-1,-1,-1,-1,-1,-1,32,-1,-1,-1,-1,-1,-1,-1,-1,-1,-1,-1,-1,-1,-1,-1,-1,-1,-1,-1,-1,-1,-1,-1,-1,-1,-1,-1,-1,-1,-1,-1,-1,-1,-1,-1,-1,-1,-1,-1,-1,-1,-1,-1,-1,-1,36,-1,-1,-1,-1,-1,-1,-1,-1,-1,-1,-1,-1,-1,-1,-1,-1,-1,-1,-1,-1,-1,-1,-1,-1,-1,-1,-1,-1,-1,-1,-1,-1,-1,-1,-1,-1,-1,-1,-1,-1,-1,-1,-1,-1,-1,-1,-1,-1,-1,-1,-1,-1,-1,-1,-1,-1,-1,-1,-1,-1,-1,-1,-1,-1,-1,-1,34,-1,-1,-1,-1,-1,-1,-1,-1,-1,-1,-1,-1,-1,-1,-1,-1,-1,-1,-1,-1,-1,-1,34,-1,-1,-1,-1,-1,-1,-1,-1,-1,-1,-1,-1,-1,-1,-1,-1,-1,-1,-1,-1,-1,-1,-1,-1,-1,-1,-1,-1,-1,-1,-1,-1,-1,-1,-1,-1,-1,-1,-1,-1,-1,-1,-1,-1,-1,-1,-1,-1,-1,-1,-1,-1,-1,-1,-1,-1,-1,-1,62,-1,-1,-1,-1,-1,-1,-1,-1,-1,-1,-1,-1,-1,-1,-1,-1,10,-1,-1,-1,-1,-1,-1,62,-1,-1,-1,-1,-1,-1,34,-1,-1,-1,-1,-1,-1,-1,-1,62,-1,-1,-1,-1,-1,-1,-1,-1,10,-1,-1,-1,-1,-1,-1,-1,-1,-1,-1,-1,-1,-1,-1,62,-1,-1,-1,-1,-1,-1,-1,-1,-1,-1,36,-1,-1,-1,-1,-1,-1,-1,-1,-1,-1,-1,-1,-1,-1,-1,-1,-1,-1,-1,-1,-1,-1,-1,-1,-1,-1,-1,-1,-1,-1,-1,-1,-1,-1,-1,-1,-1,-1,-1,-1,-1,-1,-1,-1,-1,-1,-1,-1,-1,-1,-1,-1,-1,-1,13,-1,-1,32,-1,-1,-1,-1,34,-1,-1,-1,-1,-1,-1,-1,-1,-1,-1,-1,-1,-1,-1,-1,-1,-1,-1,-1,-1,-1,-1,-1,36,-1,-1,-1,-1,-1,-1,-1,14,-1,-1,-1,-1,-1,-1,-1,-1,-1,-1,-1,-1,-1,-1,-1,-1,-1,-1,-1,-1,10,-1,-1,-1,-1,-1,-1,-1,-1,-1,-1,-1,-1,-1,-1,-1,-1,-1,-1,-1,-1,-1,-1,-1,-1,-1,-1,-1,-1,-1,-1,-1,-1,-1,-1,-1,-1,-1,-1,-1,-1,-1,-1</data>
                    </tilemap-data>
                </instance>
            </instances>
            <effects />
        </layer>
        <layer name="Characters" sid="985674740836863">
            <initially-visible>1</initially-visible>
            <background-color>255,255,255</background-color>
            <transparent>1</transparent>
            <parallax>
                <x>1</x>
                <y>1</y>
            </parallax>
            <zoom-rate>1</zoom-rate>
            <opacity>1</opacity>
            <force-own-texture>0</force-own-texture>
            <global>0</global>
            <use-render-cells>0</use-render-cells>
            <blend-mode>0</blend-mode>
            <effect-fallback>0</effect-fallback>
            <instances>
                <instance type="Pnj" uid="350">
                    <properties>
                        <initial-visibility>Visible</initial-visibility>
                        <initial-animation>question3</initial-animation>
                        <initial-frame>0</initial-frame>
                        <collisions>Enabled</collisions>
                    </properties>
                    <instance-variables>
                        <personnage>question3</personnage>
                        <type>base</type>
                        <badge></badge>
                        <answer_type>positive</answer_type>
                    </instance-variables>
                    <behavior-instances>
                        <behavior-instance type="Fade2">
                            <properties>
                                <active-at-start>No</active-at-start>
                                <fade-in-time>0</fade-in-time>
                                <wait-time>0</wait-time>
                                <fade-out-time>1</fade-out-time>
                                <destroy>After fade out</destroy>
                            </properties>
                        </behavior-instance>
                        <behavior-instance type="Solid">
                            <properties>
                                <initial-state>Enabled</initial-state>
                            </properties>
                        </behavior-instance>
                    </behavior-instances>
                    <blend-mode>0</blend-mode>
                    <effect-fallback>0</effect-fallback>
                    <world>
                        <x>1115</x>
                        <y>181</y>
                        <z>0</z>
                        <width>36</width>
                        <height>60</height>
                        <depth>0</depth>
                        <hotspotX>0.333333343</hotspotX>
                        <hotspotY>0.316666663</hotspotY>
                        <angle>0</angle>
                        <opacity>1</opacity>
                    </world>
                </instance>
                <instance type="Pnj" uid="351">
                    <properties>
                        <initial-visibility>Visible</initial-visibility>
                        <initial-animation>question2</initial-animation>
                        <initial-frame>0</initial-frame>
                        <collisions>Enabled</collisions>
                    </properties>
                    <instance-variables>
                        <personnage>question2</personnage>
                        <type>base</type>
                        <badge></badge>
                        <answer_type>negative</answer_type>
                    </instance-variables>
                    <behavior-instances>
                        <behavior-instance type="Fade2">
                            <properties>
                                <active-at-start>No</active-at-start>
                                <fade-in-time>0</fade-in-time>
                                <wait-time>0</wait-time>
                                <fade-out-time>1</fade-out-time>
                                <destroy>After fade out</destroy>
                            </properties>
                        </behavior-instance>
                        <behavior-instance type="Solid">
                            <properties>
                                <initial-state>Enabled</initial-state>
                            </properties>
                        </behavior-instance>
                    </behavior-instances>
                    <blend-mode>0</blend-mode>
                    <effect-fallback>0</effect-fallback>
                    <world>
                        <x>1122</x>
                        <y>970</y>
                        <z>0</z>
                        <width>36</width>
                        <height>48</height>
                        <depth>0</depth>
                        <hotspotX>0.527777791</hotspotX>
                        <hotspotY>0.604166687</hotspotY>
                        <angle>0</angle>
                        <opacity>1</opacity>
                    </world>
                </instance>
                <instance type="Pnj" uid="352">
                    <properties>
                        <initial-visibility>Visible</initial-visibility>
                        <initial-animation>question1</initial-animation>
                        <initial-frame>0</initial-frame>
                        <collisions>Enabled</collisions>
                    </properties>
                    <instance-variables>
                        <personnage>question1</personnage>
                        <type>base</type>
                        <badge></badge>
                        <answer_type>negative</answer_type>
                    </instance-variables>
                    <behavior-instances>
                        <behavior-instance type="Fade2">
                            <properties>
                                <active-at-start>No</active-at-start>
                                <fade-in-time>0</fade-in-time>
                                <wait-time>0</wait-time>
                                <fade-out-time>1</fade-out-time>
                                <destroy>After fade out</destroy>
                            </properties>
                        </behavior-instance>
                        <behavior-instance type="Solid">
                            <properties>
                                <initial-state>Enabled</initial-state>
                            </properties>
                        </behavior-instance>
                    </behavior-instances>
                    <blend-mode>0</blend-mode>
                    <effect-fallback>0</effect-fallback>
                    <world>
                        <x>64</x>
                        <y>881</y>
                        <z>0</z>
                        <width>32</width>
                        <height>48</height>
                        <depth>0</depth>
                        <hotspotX>0.53125</hotspotX>
                        <hotspotY>0.604166687</hotspotY>
                        <angle>0</angle>
                        <opacity>1</opacity>
                    </world>
                </instance>
                <instance type="Pnj" uid="324">
                    <properties>
                        <initial-visibility>Visible</initial-visibility>
                        <initial-animation>question4</initial-animation>
                        <initial-frame>0</initial-frame>
                        <collisions>Enabled</collisions>
                    </properties>
                    <instance-variables>
                        <personnage>question4</personnage>
                        <type>base</type>
                        <badge></badge>
                        <answer_type>positive</answer_type>
                    </instance-variables>
                    <behavior-instances>
                        <behavior-instance type="Fade2">
                            <properties>
                                <active-at-start>No</active-at-start>
                                <fade-in-time>0</fade-in-time>
                                <wait-time>0</wait-time>
                                <fade-out-time>1</fade-out-time>
                                <destroy>After fade out</destroy>
                            </properties>
                        </behavior-instance>
                        <behavior-instance type="Solid">
                            <properties>
                                <initial-state>Enabled</initial-state>
                            </properties>
                        </behavior-instance>
                    </behavior-instances>
                    <blend-mode>0</blend-mode>
                    <effect-fallback>0</effect-fallback>
                    <world>
                        <x>225</x>
                        <y>241</y>
                        <z>0</z>
                        <width>28</width>
                        <height>52</height>
                        <depth>0</depth>
                        <hotspotX>0.535714269</hotspotX>
                        <hotspotY>0.596153855</hotspotY>
                        <angle>0</angle>
                        <opacity>1</opacity>
                    </world>
                </instance>
                <instance type="Player" uid="301">
                    <properties>
                        <initial-visibility>Visible</initial-visibility>
                        <initial-animation>alex_idle_up</initial-animation>
                        <initial-frame>0</initial-frame>
                        <collisions>Enabled</collisions>
                    </properties>
                    <instance-variables>
                        <last_direction></last_direction>
                    </instance-variables>
                    <behavior-instances>
                        <behavior-instance type="ScrollTo">
                            <properties>
                                <initial-state>Enabled</initial-state>
                            </properties>
                        </behavior-instance>
                        <behavior-instance type="8Direction">
                            <properties>
                                <max-speed>200</max-speed>
                                <acceleration>5000</acceleration>
                                <deceleration>5000</deceleration>
                                <directions>4 directions</directions>
                                <set-angle>No</set-angle>
                                <default-controls>No</default-controls>
                                <initial-state>Enabled</initial-state>
                            </properties>
                        </behavior-instance>
                        <behavior-instance type="BoundToLayout">
                            <properties>
                                <bound-by>Origin</bound-by>
                            </properties>
                        </behavior-instance>
                        <behavior-instance type="ScrollTo2">
                            <properties>
                                <initial-state>Disabled</initial-state>
                            </properties>
                        </behavior-instance>
                        <behavior-instance type="MoveTo">
                            <properties>
                                <activated>No</activated>
                                <max-speed>200</max-speed>
                                <acceleration>0</acceleration>
                                <deceleration>0</deceleration>
                                <stop-by-solid>No</stop-by-solid>
                                <continued-mode>No</continued-mode>
                            </properties>
                        </behavior-instance>
                    </behavior-instances>
                    <blend-mode>0</blend-mode>
                    <effect-fallback>0</effect-fallback>
                    <world>
                        <x>769</x>
                        <y>1254</y>
                        <z>0</z>
                        <width>38</width>
                        <height>54</height>
                        <depth>0</depth>
                        <hotspotX>0.526315808</hotspotX>
                        <hotspotY>0.518518507</hotspotY>
                        <angle>0</angle>
                        <opacity>1</opacity>
                    </world>
                </instance>
            </instances>
            <effects />
        </layer>
        <layer name="Dialog" sid="452537469260386">
            <initially-visible>1</initially-visible>
            <background-color>255,255,255</background-color>
            <transparent>1</transparent>
            <parallax>
                <x>0</x>
                <y>0</y>
            </parallax>
            <zoom-rate>1</zoom-rate>
            <opacity>1</opacity>
            <force-own-texture>0</force-own-texture>
            <global>0</global>
            <use-render-cells>0</use-render-cells>
            <blend-mode>0</blend-mode>
            <effect-fallback>0</effect-fallback>
            <instances>
                <instance type="DialogBox" uid="319">
                    <properties>
                        <left-margin>16</left-margin>
                        <right-margin>16</right-margin>
                        <top-margin>16</top-margin>
                        <bottom-margin>16</bottom-margin>
                        <edges>Stretch</edges>
                        <fill>Stretch</fill>
                        <initial-visibility>Invisible</initial-visibility>
                        <hotspot>Center</hotspot>
                        <seams>Overlap</seams>
                    </properties>
                    <blend-mode>0</blend-mode>
                    <effect-fallback>0</effect-fallback>
                    <world>
                        <x>368</x>
                        <y>632</y>
                        <z>0</z>
                        <width>700</width>
                        <height>170</height>
                        <depth>0</depth>
                        <hotspotX>0.5</hotspotX>
                        <hotspotY>0.5</hotspotY>
                        <opacity>1</opacity>
                    </world>
                </instance>
                <instance type="Dialog_interieur" uid="320">
                    <properties>
                        <text>Nassim : &quot;Tu n’y vas pas avec le dos de la cuillère. Mais je trouve que tu es mal placée pour dire ça. Tu n’as que des avis tranchés et tu es assez violente dans ta façon de parler. Mais passons, il n’y a pas que ça, je pense que tu peux comprendre que toi et moi, on est victime de discrimination à cause de notre couleur, et à force d’en subir, j’ai commencé à me sentir mal. Puis j’ai rencontré de gens qui étaient dans la même situation et ils m’ont aidé, je partage leurs points de vue.&quot;</text>
                        <initial-visibility>Invisible</initial-visibility>
                        <font>Arial,-16,400,0</font>
                        <color>0,0,0</color>
                        <horizontal-alignment>Left</horizontal-alignment>
                        <vertical-alignment>Top</vertical-alignment>
                        <hotspot>Center</hotspot>
                        <wrapping>Word</wrapping>
                        <line-height>0</line-height>
                    </properties>
                    <blend-mode>0</blend-mode>
                    <effect-fallback>0</effect-fallback>
                    <world>
                        <x>368</x>
                        <y>636.481445313</y>
                        <z>0</z>
                        <width>650</width>
                        <height>142.96295166</height>
                        <depth>0</depth>
                        <hotspotX>0.5</hotspotX>
                        <hotspotY>0.5</hotspotY>
                        <angle>0</angle>
                        <opacity>1</opacity>
                    </world>
                </instance>
                <instance type="Choice" uid="335">
                    <properties>
                        <left-margin>16</left-margin>
                        <right-margin>16</right-margin>
                        <top-margin>16</top-margin>
                        <bottom-margin>16</bottom-margin>
                        <edges>Stretch</edges>
                        <fill>Stretch</fill>
                        <initial-visibility>Invisible</initial-visibility>
                        <hotspot>Center</hotspot>
                        <seams>Overlap</seams>
                    </properties>
                    <instance-variables>
                        <Choice_type>positive</Choice_type>
                    </instance-variables>
                    <blend-mode>0</blend-mode>
                    <effect-fallback>0</effect-fallback>
                    <world>
                        <x>192</x>
                        <y>480</y>
                        <z>0</z>
                        <width>348</width>
                        <height>128</height>
                        <depth>0</depth>
                        <hotspotX>0.5</hotspotX>
                        <hotspotY>0.5</hotspotY>
                        <opacity>1</opacity>
                    </world>
                </instance>
                <instance type="Choice" uid="338">
                    <properties>
                        <left-margin>16</left-margin>
                        <right-margin>16</right-margin>
                        <top-margin>16</top-margin>
                        <bottom-margin>16</bottom-margin>
                        <edges>Stretch</edges>
                        <fill>Stretch</fill>
                        <initial-visibility>Invisible</initial-visibility>
                        <hotspot>Center</hotspot>
                        <seams>Overlap</seams>
                    </properties>
                    <instance-variables>
                        <Choice_type>negative</Choice_type>
                    </instance-variables>
                    <blend-mode>0</blend-mode>
                    <effect-fallback>0</effect-fallback>
                    <world>
                        <x>544</x>
                        <y>480</y>
                        <z>0</z>
                        <width>348</width>
                        <height>128</height>
                        <depth>0</depth>
                        <hotspotX>0.5</hotspotX>
                        <hotspotY>0.5</hotspotY>
                        <opacity>1</opacity>
                    </world>
                </instance>
                <instance type="Dialog_choice" uid="339">
                    <properties>
                        <text>Oui!</text>
                        <initial-visibility>Invisible</initial-visibility>
                        <font>Arial,-16,400,0</font>
                        <color>0,0,0</color>
                        <horizontal-alignment>Center</horizontal-alignment>
                        <vertical-alignment>Center</vertical-alignment>
                        <hotspot>Center</hotspot>
                        <wrapping>Word</wrapping>
                        <line-height>0</line-height>
                    </properties>
                    <instance-variables>
                        <Choice_type>positive</Choice_type>
                    </instance-variables>
                    <blend-mode>0</blend-mode>
                    <effect-fallback>0</effect-fallback>
                    <world>
                        <x>192</x>
                        <y>480</y>
                        <z>0</z>
                        <width>314.410766602</width>
                        <height>100.005615234</height>
                        <depth>0</depth>
                        <hotspotX>0.5</hotspotX>
                        <hotspotY>0.5</hotspotY>
                        <angle>0</angle>
                        <opacity>1</opacity>
                    </world>
                </instance>
                <instance type="Dialog_choice" uid="341">
                    <properties>
                        <text>Non!</text>
                        <initial-visibility>Invisible</initial-visibility>
                        <font>Arial,-16,400,0</font>
                        <color>0,0,0</color>
                        <horizontal-alignment>Center</horizontal-alignment>
                        <vertical-alignment>Center</vertical-alignment>
                        <hotspot>Center</hotspot>
                        <wrapping>Word</wrapping>
                        <line-height>0</line-height>
                    </properties>
                    <instance-variables>
                        <Choice_type>negative</Choice_type>
                    </instance-variables>
                    <blend-mode>0</blend-mode>
                    <effect-fallback>0</effect-fallback>
                    <world>
                        <x>544</x>
                        <y>480</y>
                        <z>0</z>
                        <width>314.410766602</width>
                        <height>100.005615234</height>
                        <depth>0</depth>
                        <hotspotX>0.5</hotspotX>
                        <hotspotY>0.5</hotspotY>
                        <angle>0</angle>
                        <opacity>1</opacity>
                    </world>
                </instance>
            </instances>
            <effects />
        </layer>
        <layer name="Fade" sid="660206988661848">
            <initially-visible>1</initially-visible>
            <background-color>255,255,255</background-color>
            <transparent>1</transparent>
            <parallax>
                <x>1</x>
                <y>1</y>
            </parallax>
            <zoom-rate>1</zoom-rate>
            <opacity>1</opacity>
            <force-own-texture>0</force-own-texture>
            <global>0</global>
            <use-render-cells>0</use-render-cells>
            <blend-mode>0</blend-mode>
            <effect-fallback>0</effect-fallback>
            <instances>
                <instance type="FadeOutBlack" uid="315">
                    <properties>
                        <initial-visibility>Visible</initial-visibility>
                        <initial-animation>Default</initial-animation>
                        <initial-frame>0</initial-frame>
                        <collisions>Enabled</collisions>
                    </properties>
                    <behavior-instances>
                        <behavior-instance type="Fade">
                            <properties>
                                <active-at-start>Yes</active-at-start>
                                <fade-in-time>0</fade-in-time>
                                <wait-time>0</wait-time>
                                <fade-out-time>2</fade-out-time>
                                <destroy>No</destroy>
                            </properties>
                        </behavior-instance>
                    </behavior-instances>
                    <blend-mode>0</blend-mode>
                    <effect-fallback>0</effect-fallback>
                    <world>
                        <x>642</x>
                        <y>637</y>
                        <z>0</z>
                        <width>1296</width>
                        <height>1300</height>
                        <depth>0</depth>
                        <hotspotX>0.5</hotspotX>
                        <hotspotY>0.5</hotspotY>
                        <angle>0</angle>
                        <opacity>1</opacity>
                    </world>
                </instance>
                <instance type="FadeInBlack" uid="51">
                    <properties>
                        <initial-visibility>Visible</initial-visibility>
                        <initial-animation>Default</initial-animation>
                        <initial-frame>0</initial-frame>
                        <collisions>Enabled</collisions>
                    </properties>
                    <behavior-instances>
                        <behavior-instance type="Fade">
                            <properties>
                                <active-at-start>No</active-at-start>
                                <fade-in-time>0.5</fade-in-time>
                                <wait-time>0</wait-time>
                                <fade-out-time>0</fade-out-time>
                                <destroy>No</destroy>
                            </properties>
                        </behavior-instance>
                    </behavior-instances>
                    <blend-mode>0</blend-mode>
                    <effect-fallback>0</effect-fallback>
                    <world>
                        <x>642.5</x>
                        <y>637</y>
                        <z>0</z>
                        <width>1307</width>
                        <height>1312</height>
                        <depth>0</depth>
                        <hotspotX>0.5</hotspotX>
                        <hotspotY>0.5</hotspotY>
                        <angle>0</angle>
                        <opacity>0</opacity>
                    </world>
                </instance>
            </instances>
            <effects />
        </layer>
    </layers>
    <nonworld-instances />
    <effects />
</c2layout>
